{"name":"ParseException","commentData":{"description":"Exception throws when a Composer file is syntactically invalid","tags":[{"title":"extends","description":null,"type":null,"name":"BaseFileException"},{"title":"see","description":"See [BaseFileException]{@link module:composer-common.BaseFileException}"},{"title":"class","description":null,"type":null,"name":null},{"title":"memberof","description":"module:composer-common"}]},"methods":[{"visibility":"+","returnType":"void","name":"constructor","methodArgs":["string","string"],"decorators":["param","param"],"throws":"","example":"","commentData":{"description":"Create an ParseException","tags":[{"title":"param","description":"the message for the exception","type":{"type":"NameExpression","name":"string"},"name":"message"},{"title":"param","description":"the optional file location associated with the exception","type":{"type":"NameExpression","name":"string"},"name":"fileLocation"}]},"description":["Create an ParseException"],"parameters":[{"description":"the message for the exception","type":"string","name":"message","optional":true},{"description":"the optional file location associated with the exception","type":"string","name":"fileLocation","optional":true}]}],"superClass":"BaseFileException","description":["Exception throws when a Composer file is syntactically invalid"],"seeAlso":["See [BaseFileException](basefileexception)"],"visibility":"public","extends":"BaseFileException","module":"common"}